anyvec/client.py
anyvec/exceptions.py
anyvec/models.py
anyvec/processing/audio/audio_mime_maps.py
anyvec/processing/audio/audio_transcribe.py
anyvec/processing/code/code_mime_maps.py
anyvec/processing/code/code_vectorize.py
anyvec/processing/document/doc_mime_maps.py
anyvec/processing/document/document_extract.py
anyvec/processing/document/document_markdown.py
anyvec/processing/document/document_ocr.py
anyvec/processing/document/document_office.py
anyvec/processing/document/document_pdf.py
anyvec/processing/document/document_pdf_to_vec.py
anyvec/processing/document/epub.py
anyvec/processing/image/image_conversion.py
anyvec/processing/image/image_mime_maps.py
anyvec/processing/image/image_ocr_and_vectorize.py
anyvec/processing/processor.py
anyvec/processing/utils.py
anyvec/processing/video/extract_video.py
anyvec/processing/video/video_mime_maps.py
anyvec/tests.py
anyvec/vectorization.py
anyvec-0.1.8.dist-info/LICENSE
anyvec-0.1.8.dist-info/METADATA
anyvec-0.1.8.dist-info/WHEEL
anyvec-0.1.8.dist-info/RECORD
