Metadata-Version: 2.3
Name: anyvec
Version: 0.1.8
Summary: A Python package for seamless vectorization for any content type
Author: Mark Shteyn
Author-email: markshteyn1@gmail.com
Requires-Python: >=3.10,<4.0
Classifier: Programming Language :: Python :: 3
Classifier: Programming Language :: Python :: 3.10
Classifier: Programming Language :: Python :: 3.11
Classifier: Programming Language :: Python :: 3.12
Classifier: Programming Language :: Python :: 3.13
Provides-Extra: audio
Requires-Dist: av (==14.3.0)
Requires-Dist: beautifulsoup4 (==4.13.4)
Requires-Dist: ebooklib (==0.19)
Requires-Dist: mammoth (==1.9.0)
Requires-Dist: markdown (==3.8)
Requires-Dist: moviepy (==2.1.2)
Requires-Dist: numpy (==2.2.5)
Requires-Dist: odfpy (==1.4.1)
Requires-Dist: opencv-python (==4.11.0.86)
Requires-Dist: openpyxl (==3.1.5)
Requires-Dist: pdfkit (==1.0.0)
Requires-Dist: pdfplumber (==0.11.6)
Requires-Dist: pillow (==10.4.0)
Requires-Dist: pillow-avif-plugin (==1.5.2)
Requires-Dist: pillow-heif (==0.22.0)
Requires-Dist: pymupdf (==1.25.5)
Requires-Dist: python-docx (==1.1.0)
Requires-Dist: python-pptx (==1.0.2)
Requires-Dist: requests (==2.32.3)
Requires-Dist: ruff (==0.11.8)
Requires-Dist: striprtf (>=0.0.29,<0.0.30)
Requires-Dist: wand (==0.6.13)
Requires-Dist: weasyprint (==65.1)
Requires-Dist: xlrd (==2.0.1)
